{"version": 0.6, "generator": "Overpass API 0.7.62.7 375dc00a", "osm3s": {"timestamp_osm_base": "2025-06-16T09:04:14Z", "copyright": "The data included in this document is from www.openstreetmap.org. The data is made available under ODbL."}, "elements": [{"type": "node", "id": 276658497, "lat": 40.3476921, "lon": 18.1847491, "tags": {"highway": "traffic_signals"}}, {"type": "node", "id": 277150881, "lat": 40.3783502, "lon": 18.2618248, "tags": {"highway": "traffic_signals"}}, {"type": "node", "id": 321456856, "lat": 40.2982408, "lon": 18.160582, "tags": {"crossing": "no", "highway": "traffic_signals"}}, {"type": "node", "id": 321457072, "lat": 40.3667697, "lon": 18.2200868, "tags": {"crossing": "no", "highway": "traffic_signals"}}, {"type": "node", "id": 331292592, "lat": 40.3071774, "lon": 18.3966592, "tags": {"highway": "traffic_signals"}}, {"type": "node", "id": 331293510, "lat": 40.2929146, "lon": 18.4214634, "tags": {"highway": "traffic_signals"}}, {"type": "node", "id": 376078454, "lat": 40.3662222, "lon": 18.2063337, "tags": {"highway": "traffic_signals"}}, {"type": "node", "id": 376080330, "lat": 40.3613473, "lon": 18.1880793, "tags": {"highway": "traffic_signals"}}, {"type": "node", "id": 376082899, "lat": 40.3627336, "lon": 18.1749713, "tags": {"highway": "traffic_signals"}}, {"type": "node", "id": 376320343, "lat": 40.343158, "lon": 18.1591715, "tags": {"highway": "traffic_signals"}}, {"type": "node", "id": 414994881, "lat": 40.3617166, "lon": 18.1537437, "tags": {"highway": "traffic_signals"}}, {"type": "node", "id": 414994931, "lat": 40.4001004, "lon": 18.0112222, "tags": {"highway": "traffic_signals"}}, {"type": "node", "id": 458593694, "lat": 40.3782569, "lon": 18.2618657, "tags": {"highway": "traffic_signals"}}, {"type": "node", "id": 458739697, "lat": 40.3712929, "lon": 18.2360981, "tags": {"highway": "traffic_signals"}}, {"type": "node", "id": 458739700, "lat": 40.3819042, "lon": 18.2750949, "tags": {"highway": "traffic_signals"}}, {"type": "node", "id": 458739702, "lat": 40.3856477, "lon": 18.2890848, "tags": {"highway": "traffic_signals"}}, {"type": "node", "id": 458739723, "lat": 40.3818252, "lon": 18.2751344, "tags": {"highway": "traffic_signals"}}, {"type": "node", "id": 458739724, "lat": 40.385566, "lon": 18.2891245, "tags": {"highway": "traffic_signals"}}, {"type": "node", "id": 458745355, "lat": 40.3126786, "lon": 18.2001283, "tags": {"highway": "traffic_signals", "traffic_signals": "signal"}}, {"type": "node", "id": 471182091, "lat": 40.3201108, "lon": 18.1851653, "tags": {"highway": "traffic_signals"}}, {"type": "node", "id": 471204385, "lat": 40.3017997, "lon": 18.1547274, "tags": {"highway": "traffic_signals"}}, {"type": "node", "id": 471204393, "lat": 40.3046298, "lon": 18.1566549, "tags": {"crossing": "no", "highway": "traffic_signals"}}, {"type": "node", "id": 472406020, "lat": 40.3501907, "lon": 18.1519703, "tags": {"highway": "traffic_signals"}}, {"type": "node", "id": 472406055, "lat": 40.3547909, "lon": 18.1517034, "tags": {"highway": "traffic_signals"}}, {"type": "node", "id": 472406074, "lat": 40.3376773, "lon": 18.1681914, "tags": {"highway": "traffic_signals"}}, {"type": "node", "id": 472406169, "lat": 40.3004304, "lon": 18.1545402, "tags": {"highway": "traffic_signals"}}, {"type": "node", "id": 473555506, "lat": 40.3425662, "lon": 18.1756509, "tags": {"highway": "traffic_signals"}}, {"type": "node", "id": 473555540, "lat": 40.3483249, "lon": 18.1732037, "tags": {"highway": "traffic_signals"}}, {"type": "node", "id": 473555542, "lat": 40.3490405, "lon": 18.1741378, "tags": {"highway": "traffic_signals"}}, {"type": "node", "id": 473555583, "lat": 40.3554102, "lon": 18.1781475, "tags": {"highway": "traffic_signals"}}, {"type": "node", "id": 473555762, "lat": 40.3589078, "lon": 18.1729841, "tags": {"direction": "backward", "highway": "traffic_signals"}}, {"type": "node", "id": 473555871, "lat": 40.3394963, "lon": 18.1769661, "tags": {"highway": "traffic_signals"}}, {"type": "node", "id": 473612610, "lat": 40.2721448, "lon": 18.2602931, "tags": {"highway": "traffic_signals"}}, {"type": "node", "id": 476031838, "lat": 40.347178, "lon": 18.1537018, "tags": {"highway": "traffic_signals"}}, {"type": "node", "id": 476355699, "lat": 40.3534701, "lon": 18.1740398, "tags": {"highway": "traffic_signals"}}, {"type": "node", "id": 493756397, "lat": 40.2884198, "lon": 18.0072181, "tags": {"highway": "traffic_signals"}}, {"type": "node", "id": 523704690, "lat": 40.3377957, "lon": 18.1682115, "tags": {"highway": "traffic_signals"}}, {"type": "node", "id": 523704796, "lat": 40.3316296, "lon": 18.1662956, "tags": {"highway": "traffic_signals"}}, {"type": "node", "id": 552874696, "lat": 40.3681553, "lon": 18.3100336, "tags": {"highway": "traffic_signals"}}, {"type": "node", "id": 554645315, "lat": 40.3439746, "lon": 18.1578579, "tags": {"highway": "traffic_signals"}}, {"type": "node", "id": 554649402, "lat": 40.2792607, "lon": 18.3443602, "tags": {"direction": "backward", "highway": "traffic_signals"}}, {"type": "node", "id": 554649435, "lat": 40.279296, "lon": 18.3441907, "tags": {"highway": "traffic_signals"}}, {"type": "node", "id": 600030201, "lat": 40.3571215, "lon": 18.1860137, "tags": {"highway": "traffic_signals"}}, {"type": "node", "id": 605288990, "lat": 40.5081376, "lon": 18.0918149, "tags": {"highway": "traffic_signals", "traffic_signals": "signal"}}, {"type": "node", "id": 642573018, "lat": 40.339523, "lon": 18.1571999, "tags": {"highway": "traffic_signals"}}, {"type": "node", "id": 642573263, "lat": 40.3414293, "lon": 18.162078, "tags": {"highway": "traffic_signals"}}, {"type": "node", "id": 642575995, "lat": 40.3441334, "lon": 18.1446583, "tags": {"highway": "traffic_signals"}}, {"type": "node", "id": 642580337, "lat": 40.3628531, "lon": 18.150531, "tags": {"highway": "traffic_signals"}}, {"type": "node", "id": 642586762, "lat": 40.3555052, "lon": 18.1794806, "tags": {"highway": "traffic_signals"}}, {"type": "node", "id": 642588369, "lat": 40.3560898, "lon": 18.1824019, "tags": {"highway": "traffic_signals"}}, {"type": "node", "id": 642589188, "lat": 40.3577579, "lon": 18.1912842, "tags": {"highway": "traffic_signals"}}, {"type": "node", "id": 642589536, "lat": 40.3616159, "lon": 18.1851872, "tags": {"highway": "traffic_signals"}}, {"type": "node", "id": 642594015, "lat": 40.3712259, "lon": 18.1782241, "tags": {"highway": "traffic_signals"}}, {"type": "node", "id": 642594030, "lat": 40.3642853, "lon": 18.1851506, "tags": {"highway": "traffic_signals"}}, {"type": "node", "id": 642594159, "lat": 40.368177, "lon": 18.1834362, "tags": {"highway": "traffic_signals"}}, {"type": "node", "id": 642594650, "lat": 40.3652873, "lon": 18.1884109, "tags": {"highway": "traffic_signals"}}, {"type": "node", "id": 750086560, "lat": 40.4844343, "lon": 17.9887925, "tags": {"highway": "traffic_signals"}}, {"type": "node", "id": 760310954, "lat": 40.3909078, "lon": 18.1261231, "tags": {"highway": "traffic_signals"}}, {"type": "node", "id": 761862371, "lat": 40.3880314, "lon": 18.1331293, "tags": {"highway": "traffic_signals", "traffic_signals:direction": "both"}}, {"type": "node", "id": 762931689, "lat": 40.3343272, "lon": 18.1791556, "tags": {"highway": "traffic_signals"}}, {"type": "node", "id": 763161393, "lat": 40.3331616, "lon": 18.1667546, "tags": {"highway": "traffic_signals"}}, {"type": "node", "id": 833762583, "lat": 40.3092655, "lon": 18.201982, "tags": {"highway": "traffic_signals", "traffic_signals": "signal"}}, {"type": "node", "id": 833762590, "lat": 40.3109067, "lon": 18.205422, "tags": {"highway": "traffic_signals", "traffic_signals": "signal"}}, {"type": "node", "id": 833762596, "lat": 40.3130633, "lon": 18.1964726, "tags": {"highway": "traffic_signals", "traffic_signals": "signal"}}, {"type": "node", "id": 833771014, "lat": 40.3094406, "lon": 18.2093154, "tags": {"highway": "traffic_signals", "traffic_signals": "signal"}}, {"type": "node", "id": 837977583, "lat": 40.4379993, "lon": 18.0341245, "tags": {"highway": "traffic_signals"}}, {"type": "node", "id": 837977689, "lat": 40.4064398, "lon": 18.0698117, "tags": {"highway": "traffic_signals"}}, {"type": "node", "id": 837978869, "lat": 40.4396421, "lon": 18.0370513, "tags": {"highway": "traffic_signals"}}, {"type": "node", "id": 837978944, "lat": 40.4352109, "lon": 18.0405075, "tags": {"highway": "traffic_signals"}}, {"type": "node", "id": 837979500, "lat": 40.4380306, "lon": 18.0477225, "tags": {"highway": "traffic_signals"}}, {"type": "node", "id": 837979962, "lat": 40.4331213, "lon": 18.0421266, "tags": {"highway": "traffic_signals"}}, {"type": "node", "id": 876271634, "lat": 40.3092046, "lon": 18.1296713, "tags": {"highway": "traffic_signals"}}, {"type": "node", "id": 882404813, "lat": 40.3309822, "lon": 18.115617, "tags": {"highway": "traffic_signals"}}, {"type": "node", "id": 883370697, "lat": 40.4913211, "lon": 17.9887719, "tags": {"highway": "traffic_signals"}}, {"type": "node", "id": 886781556, "lat": 40.3953038, "lon": 18.0204706, "tags": {"highway": "traffic_signals"}}, {"type": "node", "id": 890456047, "lat": 40.4413958, "lon": 18.03567, "tags": {"highway": "traffic_signals"}}, {"type": "node", "id": 914742248, "lat": 40.4002104, "lon": 18.0226296, "tags": {"highway": "traffic_signals"}}, {"type": "node", "id": 968052281, "lat": 40.3848165, "lon": 18.1448781, "tags": {"highway": "traffic_signals"}}, {"type": "node", "id": 1111319758, "lat": 40.3315124, "lon": 18.1662601, "tags": {"highway": "traffic_signals"}}, {"type": "node", "id": 1112277411, "lat": 40.3288803, "lon": 18.1653824, "tags": {"highway": "traffic_signals"}}, {"type": "node", "id": 1112277541, "lat": 40.3290165, "lon": 18.1654918, "tags": {"direction": "backward", "highway": "traffic_signals"}}, {"type": "node", "id": 1112277992, "lat": 40.3287176, "lon": 18.1654068, "tags": {"direction": "forward", "highway": "traffic_signals"}}, {"type": "node", "id": 1423874710, "lat": 40.3619158, "lon": 18.1531642, "tags": {"highway": "traffic_signals"}}, {"type": "node", "id": 1427817213, "lat": 40.3657409, "lon": 18.1424107, "tags": {"highway": "traffic_signals"}}, {"type": "node", "id": 1459406340, "lat": 40.3542917, "lon": 18.1655936, "tags": {"highway": "traffic_signals"}}, {"type": "node", "id": 1460490351, "lat": 40.306724, "lon": 18.1824467, "tags": {"highway": "traffic_signals"}}, {"type": "node", "id": 1460490495, "lat": 40.3312174, "lon": 18.1661772, "tags": {"highway": "traffic_signals"}}, {"type": "node", "id": 1490044375, "lat": 40.4796903, "lon": 17.9986198, "tags": {"highway": "traffic_signals"}}, {"type": "node", "id": 1736547335, "lat": 40.2878419, "lon": 18.0095933, "tags": {"highway": "traffic_signals"}}, {"type": "node", "id": 1814632676, "lat": 40.4993708, "lon": 18.0038107, "tags": {"highway": "traffic_signals"}}, {"type": "node", "id": 1814632718, "lat": 40.4993092, "lon": 18.0039593, "tags": {"highway": "traffic_signals"}}, {"type": "node", "id": 2091110105, "lat": 40.3694331, "lon": 18.3091771, "tags": {"highway": "traffic_signals"}}, {"type": "node", "id": 2130326713, "lat": 40.3479457, "lon": 18.1847557, "tags": {"highway": "traffic_signals"}}, {"type": "node", "id": 2130326725, "lat": 40.3479836, "lon": 18.1849509, "tags": {"highway": "traffic_signals"}}, {"type": "node", "id": 2130331037, "lat": 40.3477919, "lon": 18.1848961, "tags": {"direction": "backward", "highway": "traffic_signals"}}, {"type": "node", "id": 2130356359, "lat": 40.3507827, "lon": 18.1856133, "tags": {"direction": "backward", "highway": "traffic_signals"}}, {"type": "node", "id": 2130356363, "lat": 40.3510254, "lon": 18.1857901, "tags": {"highway": "traffic_signals"}}, {"type": "node", "id": 2130356373, "lat": 40.3509842, "lon": 18.1860478, "tags": {"direction": "forward", "highway": "traffic_signals"}}, {"type": "node", "id": 2130356377, "lat": 40.3506843, "lon": 18.185852, "tags": {"highway": "traffic_signals"}}, {"type": "node", "id": 2198015289, "lat": 40.354231, "lon": 18.1657569, "tags": {"highway": "traffic_signals"}}, {"type": "node", "id": 2378913715, "lat": 40.3567584, "lon": 18.1743232, "tags": {"highway": "traffic_signals"}}, {"type": "node", "id": 2425961297, "lat": 40.3378061, "lon": 18.1680439, "tags": {"highway": "traffic_signals"}}, {"type": "node", "id": 2425961298, "lat": 40.3378879, "lon": 18.1680752, "tags": {"highway": "traffic_signals"}}, {"type": "node", "id": 2541248444, "lat": 40.3461095, "lon": 18.1901698, "tags": {"direction": "forward", "highway": "traffic_signals"}}, {"type": "node", "id": 2541248445, "lat": 40.3462916, "lon": 18.190118, "tags": {"direction": "forward", "highway": "traffic_signals"}}, {"type": "node", "id": 2651993381, "lat": 40.3978551, "lon": 18.0238473, "tags": {"highway": "traffic_signals"}}, {"type": "node", "id": 2837642349, "lat": 40.2790988, "lon": 18.3441248, "tags": {"direction": "forward", "highway": "traffic_signals"}}, {"type": "node", "id": 2917398241, "lat": 40.3219469, "lon": 18.0728823, "tags": {"highway": "traffic_signals"}}, {"type": "node", "id": 2921714244, "lat": 40.3130157, "lon": 18.196579, "tags": {"highway": "traffic_signals", "traffic_signals": "signal"}}, {"type": "node", "id": 2946678790, "lat": 40.3535854, "lon": 18.1763741, "tags": {"highway": "traffic_signals"}}, {"type": "node", "id": 2946678792, "lat": 40.3535939, "lon": 18.1765048, "tags": {"highway": "traffic_signals"}}, {"type": "node", "id": 2955624975, "lat": 40.3712787, "lon": 18.2362546, "tags": {"highway": "traffic_signals"}}, {"type": "node", "id": 2955624993, "lat": 40.3714425, "lon": 18.2363217, "tags": {"highway": "traffic_signals"}}, {"type": "node", "id": 2962218938, "lat": 40.3616411, "lon": 18.1881641, "tags": {"highway": "traffic_signals"}}, {"type": "node", "id": 2967503802, "lat": 40.3534324, "lon": 18.1857943, "tags": {"highway": "traffic_signals"}}, {"type": "node", "id": 2967503820, "lat": 40.3552156, "lon": 18.1848523, "tags": {"highway": "traffic_signals"}}, {"type": "node", "id": 2986350140, "lat": 40.3661041, "lon": 18.2063582, "tags": {"highway": "traffic_signals"}}, {"type": "node", "id": 2986350152, "lat": 40.3669328, "lon": 18.2203353, "tags": {"highway": "traffic_signals"}}, {"type": "node", "id": 2986350154, "lat": 40.366961, "lon": 18.2202399, "tags": {"highway": "traffic_signals"}}, {"type": "node", "id": 2990469801, "lat": 40.346153, "lon": 18.1902735, "tags": {"direction": "backward", "highway": "traffic_signals"}}, {"type": "node", "id": 2990469815, "lat": 40.3463115, "lon": 18.1898045, "tags": {"direction": "forward", "highway": "traffic_signals"}}, {"type": "node", "id": 2990469824, "lat": 40.3467804, "lon": 18.1881483, "tags": {"highway": "traffic_signals"}}, {"type": "node", "id": 2990469826, "lat": 40.3468027, "lon": 18.1882206, "tags": {"direction": "backward", "highway": "traffic_signals"}}, {"type": "node", "id": 2990469831, "lat": 40.3469028, "lon": 18.1878847, "tags": {"direction": "forward", "highway": "traffic_signals"}}, {"type": "node", "id": 2990469834, "lat": 40.34694, "lon": 18.1879652, "tags": {"direction": "forward", "highway": "traffic_signals"}}, {"type": "node", "id": 2999776240, "lat": 40.3479655, "lon": 18.1677903, "tags": {"highway": "traffic_signals"}}, {"type": "node", "id": 2999776242, "lat": 40.3480277, "lon": 18.1678824, "tags": {"direction": "backward", "highway": "traffic_signals"}}, {"type": "node", "id": 2999776250, "lat": 40.348116, "lon": 18.167905, "tags": {"highway": "traffic_signals"}}, {"type": "node", "id": 2999776251, "lat": 40.3481803, "lon": 18.1676261, "tags": {"direction": "forward", "highway": "traffic_signals"}}, {"type": "node", "id": 2999776253, "lat": 40.3482313, "lon": 18.1677397, "tags": {"highway": "traffic_signals"}}, {"type": "node", "id": 3112910243, "lat": 40.3122391, "lon": 18.1618155, "tags": {"highway": "traffic_signals"}}, {"type": "node", "id": 3130899833, "lat": 40.2919817, "lon": 18.3043811, "tags": {"highway": "traffic_signals"}}, {"type": "node", "id": 3177041464, "lat": 40.3516679, "lon": 18.1641866, "tags": {"crossing": "traffic_signals", "crossing_ref": "zebra", "highway": "traffic_signals", "traffic_signals:sound": "yes"}}, {"type": "node", "id": 3177041465, "lat": 40.3517343, "lon": 18.1639989, "tags": {"crossing": "traffic_signals", "crossing_ref": "zebra", "highway": "traffic_signals", "traffic_signals:sound": "yes"}}, {"type": "node", "id": 3181151499, "lat": 40.3588373, "lon": 18.1730285, "tags": {"direction": "forward", "highway": "traffic_signals"}}, {"type": "node", "id": 3193699771, "lat": 40.256474, "lon": 18.2852152, "tags": {"highway": "traffic_signals"}}, {"type": "node", "id": 3221659661, "lat": 40.3522966, "lon": 18.1859538, "tags": {"highway": "traffic_signals"}}, {"type": "node", "id": 3221659662, "lat": 40.3523555, "lon": 18.1857483, "tags": {"highway": "traffic_signals"}}, {"type": "node", "id": 3221659663, "lat": 40.3523755, "lon": 18.1860247, "tags": {"highway": "traffic_signals"}}, {"type": "node", "id": 3221659664, "lat": 40.3524453, "lon": 18.1858369, "tags": {"highway": "traffic_signals"}}, {"type": "node", "id": 3385394678, "lat": 40.3848101, "lon": 18.1449659, "tags": {"direction": "backward", "highway": "traffic_signals"}}, {"type": "node", "id": 3385394681, "lat": 40.3849366, "lon": 18.1449618, "tags": {"highway": "traffic_signals"}}, {"type": "node", "id": 3385394682, "lat": 40.3849427, "lon": 18.1448773, "tags": {"direction": "forward", "highway": "traffic_signals"}}, {"type": "node", "id": 3404728184, "lat": 40.3543089, "lon": 18.1763021, "tags": {"highway": "traffic_signals"}}, {"type": "node", "id": 3404728185, "lat": 40.3543106, "lon": 18.1764372, "tags": {"highway": "traffic_signals"}}, {"type": "node", "id": 3404728186, "lat": 40.3543703, "lon": 18.1762379, "tags": {"highway": "traffic_signals"}}, {"type": "node", "id": 3747503225, "lat": 40.3398457, "lon": 18.1649649, "tags": {"highway": "traffic_signals"}}, {"type": "node", "id": 3747503425, "lat": 40.3395026, "lon": 18.1651841, "tags": {"highway": "traffic_signals"}}, {"type": "node", "id": 3747503525, "lat": 40.339803, "lon": 18.1647871, "tags": {"direction": "forward", "highway": "traffic_signals"}}, {"type": "node", "id": 3914750164, "lat": 40.3620319, "lon": 18.1718058, "tags": {"highway": "traffic_signals"}}, {"type": "node", "id": 3914750165, "lat": 40.3621229, "lon": 18.1721415, "tags": {"highway": "traffic_signals"}}, {"type": "node", "id": 3914750167, "lat": 40.3622958, "lon": 18.1718805, "tags": {"highway": "traffic_signals"}}, {"type": "node", "id": 3914750179, "lat": 40.3623376, "lon": 18.172073, "tags": {"highway": "traffic_signals"}}, {"type": "node", "id": 3921587995, "lat": 40.347029, "lon": 18.1535923, "tags": {"highway": "traffic_signals"}}, {"type": "node", "id": 3933127101, "lat": 40.3623662, "lon": 18.1764842, "tags": {"highway": "traffic_signals"}}, {"type": "node", "id": 3933127103, "lat": 40.3624774, "lon": 18.1765966, "tags": {"direction": "forward", "highway": "traffic_signals"}}, {"type": "node", "id": 4124559765, "lat": 40.3373905, "lon": 18.1680093, "tags": {"direction": "forward", "highway": "traffic_signals"}}, {"type": "node", "id": 4342596314, "lat": 40.3537624, "lon": 18.1854016, "tags": {"highway": "traffic_signals"}}, {"type": "node", "id": 4342596315, "lat": 40.3539355, "lon": 18.1854588, "tags": {"highway": "traffic_signals"}}, {"type": "node", "id": 4342596316, "lat": 40.3549767, "lon": 18.1851015, "tags": {"highway": "traffic_signals"}}, {"type": "node", "id": 4342596318, "lat": 40.3551253, "lon": 18.1852181, "tags": {"highway": "traffic_signals"}}, {"type": "node", "id": 4342596326, "lat": 40.3610375, "lon": 18.1802132, "tags": {"highway": "traffic_signals"}}, {"type": "node", "id": 4342596330, "lat": 40.3611419, "lon": 18.1798442, "tags": {"highway": "traffic_signals"}}, {"type": "node", "id": 4342596331, "lat": 40.3612089, "lon": 18.1801469, "tags": {"direction": "backward", "highway": "traffic_signals"}}, {"type": "node", "id": 4342596334, "lat": 40.3622848, "lon": 18.177185, "tags": {"highway": "traffic_signals"}}, {"type": "node", "id": 4342596336, "lat": 40.3623615, "lon": 18.1770543, "tags": {"direction": "backward", "highway": "traffic_signals"}}, {"type": "node", "id": 4342596339, "lat": 40.3626166, "lon": 18.1749818, "tags": {"highway": "traffic_signals"}}, {"type": "node", "id": 4342596341, "lat": 40.3627252, "lon": 18.1754339, "tags": {"highway": "traffic_signals"}}, {"type": "node", "id": 4809770627, "lat": 40.2791015, "lon": 18.3439161, "tags": {"direction": "forward", "highway": "traffic_signals"}}, {"type": "node", "id": 4809770628, "lat": 40.2791271, "lon": 18.344231, "tags": {"direction": "forward", "highway": "traffic_signals"}}, {"type": "node", "id": 4946817494, "lat": 40.2748232, "lon": 18.4244511, "tags": {"highway": "traffic_signals", "traffic_signals:direction": "forward"}}, {"type": "node", "id": 4946817495, "lat": 40.274774, "lon": 18.4248128, "tags": {"highway": "traffic_signals", "traffic_signals:direction": "backward"}}, {"type": "node", "id": 4946817496, "lat": 40.2749242, "lon": 18.424594, "tags": {"highway": "traffic_signals"}}, {"type": "node", "id": 4946817497, "lat": 40.2746906, "lon": 18.4246601, "tags": {"highway": "traffic_signals"}}, {"type": "node", "id": 4995278495, "lat": 40.3045619, "lon": 18.1565233, "tags": {"highway": "traffic_signals"}}, {"type": "node", "id": 4995278498, "lat": 40.3044904, "lon": 18.1564532, "tags": {"highway": "traffic_signals"}}, {"type": "node", "id": 5741005203, "lat": 40.2920947, "lon": 18.3044976, "tags": {"highway": "traffic_signals"}}, {"type": "node", "id": 5741005204, "lat": 40.2922229, "lon": 18.3042543, "tags": {"highway": "traffic_signals"}}, {"type": "node", "id": 5741005205, "lat": 40.2923233, "lon": 18.3043219, "tags": {"highway": "traffic_signals"}}, {"type": "node", "id": 5772794895, "lat": 40.3694357, "lon": 18.3089008, "tags": {"highway": "traffic_signals"}}, {"type": "node", "id": 5772794896, "lat": 40.3691888, "lon": 18.3091222, "tags": {"highway": "traffic_signals"}}, {"type": "node", "id": 6464307298, "lat": 40.361383, "lon": 18.1882726, "tags": {"highway": "traffic_signals"}}, {"type": "node", "id": 6464307299, "lat": 40.3616983, "lon": 18.1883683, "tags": {"highway": "traffic_signals"}}, {"type": "node", "id": 7159411816, "lat": 40.3086012, "lon": 18.2115489, "tags": {"highway": "traffic_signals", "traffic_signals": "signal"}}, {"type": "node", "id": 7836896287, "lat": 40.3545704, "lon": 18.1726022, "tags": {"highway": "traffic_signals"}}, {"type": "node", "id": 8636389492, "lat": 40.3662739, "lon": 18.2063901, "tags": {"bicycle": "yes", "highway": "traffic_signals", "traffic_signals": "signal", "traffic_signals:direction": "backward"}}, {"type": "node", "id": 9715959310, "lat": 40.3177999, "lon": 18.0895982, "tags": {"highway": "traffic_signals"}}, {"type": "node", "id": 9715959316, "lat": 40.3249348, "lon": 18.0940857, "tags": {"highway": "traffic_signals"}}, {"type": "node", "id": 9718135960, "lat": 40.2982498, "lon": 18.224754, "tags": {"highway": "traffic_signals"}}, {"type": "node", "id": 9721015960, "lat": 40.2736039, "lon": 18.0484315, "tags": {"highway": "traffic_signals"}}, {"type": "node", "id": 9721015969, "lat": 40.2732927, "lon": 18.0429812, "tags": {"highway": "traffic_signals"}}, {"type": "node", "id": 9721015971, "lat": 40.2735628, "lon": 18.0483315, "tags": {"highway": "traffic_signals"}}, {"type": "node", "id": 9721015972, "lat": 40.2736147, "lon": 18.0482851, "tags": {"highway": "traffic_signals"}}, {"type": "node", "id": 9721015973, "lat": 40.2735816, "lon": 18.0482127, "tags": {"highway": "traffic_signals"}}]}